README.rst
setup.cfg
setup.py
traptor/__init__.py
traptor/dd_monitoring.py
traptor/healthcheck.py
traptor/rule_set.py
traptor/settings.py
traptor/traptor.py
traptor/traptor_birdy.py
traptor/traptor_limit_counter.py
traptor/version.py
traptor.egg-info/PKG-INFO
traptor.egg-info/SOURCES.txt
traptor.egg-info/dependency_links.txt
traptor.egg-info/requires.txt
traptor.egg-info/top_level.txt
traptor.egg-info/zip-safe