Metadata-Version: 2.1
Name: traptor
Version: 3.3.4
Summary: A distributed twitter streaming service
Home-page: https://github.com/istresearch/traptor
Author: Jason Haas
Author-email: jasonrhaas@gmail.com
License: MIT
Keywords: twitter,distributed,kafka,ansible,redis
Platform: UNKNOWN
Provides-Extra: test
Provides-Extra: docs
Provides-Extra: all
Provides-Extra: lint
